odoo/addons/purchase_requisition_line_description/README.rst
odoo/addons/purchase_requisition_line_description/__init__.py
odoo/addons/purchase_requisition_line_description/__manifest__.py
odoo/addons/purchase_requisition_line_description/i18n/it.po
odoo/addons/purchase_requisition_line_description/i18n/pt_BR.po
odoo/addons/purchase_requisition_line_description/i18n/purchase_requisition_line_description.pot
odoo/addons/purchase_requisition_line_description/models/__init__.py
odoo/addons/purchase_requisition_line_description/models/purchase_requisition_line.py
odoo/addons/purchase_requisition_line_description/readme/CONTRIBUTORS.md
odoo/addons/purchase_requisition_line_description/readme/DESCRIPTION.md
odoo/addons/purchase_requisition_line_description/readme/USAGE.md
odoo/addons/purchase_requisition_line_description/report/purchase_requisition_report.xml
odoo/addons/purchase_requisition_line_description/static/description/icon.png
odoo/addons/purchase_requisition_line_description/static/description/index.html
odoo/addons/purchase_requisition_line_description/tests/__init__.py
odoo/addons/purchase_requisition_line_description/tests/test_purchase_requisition_line_description.py
odoo/addons/purchase_requisition_line_description/views/purchase_requisition.xml
odoo_addon_purchase_requisition_line_description-18.0.1.0.0.5.dist-info/METADATA
odoo_addon_purchase_requisition_line_description-18.0.1.0.0.5.dist-info/WHEEL
odoo_addon_purchase_requisition_line_description-18.0.1.0.0.5.dist-info/top_level.txt
odoo_addon_purchase_requisition_line_description-18.0.1.0.0.5.dist-info/RECORD
